LICENSE
MANIFEST.in
README.md
setup.py
DexBuyTools.egg-info/PKG-INFO
DexBuyTools.egg-info/SOURCES.txt
DexBuyTools.egg-info/dependency_links.txt
DexBuyTools.egg-info/entry_points.txt
DexBuyTools.egg-info/requires.txt
DexBuyTools.egg-info/top_level.txt
dexbuytools/__init__.py
dexbuytools/__main__.py
dexbuytools/config/__init__.py
dexbuytools/config/buy_params.yml
dexbuytools/config/general_params.yml
dexbuytools/config/wallet_data_template.yml
dexbuytools/helpers/AvaxHelper.py
dexbuytools/helpers/BscHelper.py
dexbuytools/helpers/EthHelper.py
dexbuytools/helpers/EvmBaseHelper.py
dexbuytools/helpers/FtmHelper.py
dexbuytools/helpers/PolyHelper.py
dexbuytools/helpers/__init__.py
dexbuytools/helpers/data/__init__.py
dexbuytools/helpers/data/avax.py
dexbuytools/helpers/data/bsc.py
dexbuytools/helpers/data/eth.py
dexbuytools/helpers/data/ftm.py
dexbuytools/helpers/data/general.py
dexbuytools/helpers/data/poly.py
dexbuytools/log_utils/__init__.py