Metadata-Version: 2.1
Name: DexBuyTools
Version: 0.1.post9
Summary: CLI-application to perform buys on various decentralized exchanges and different networks
Home-page: UNKNOWN
Author: minhtrng
Author-email: minhtrng0x@gmail.com
License: MIT
Platform: UNKNOWN
License-File: LICENSE
